cli/README.md
cli/__init__.py
cli/main.py
lf_algorithm/__init__.py
lf_algorithm/agent_manager.py
lf_algorithm/framework_agent.py
lf_algorithm/models/models.py
lf_algorithm/plugins/__init__.py
lf_algorithm/plugins/airflow_lineage_agent/__init__.py
lf_algorithm/plugins/airflow_lineage_agent/airflow_instructions.py
lf_algorithm/plugins/airflow_lineage_agent/lineage_agent.py
lf_algorithm/plugins/airflow_lineage_agent/mcp_servers/__init__.py
lf_algorithm/plugins/airflow_lineage_agent/mcp_servers/mcp_params.py
lf_algorithm/plugins/airflow_lineage_agent/mcp_servers/mcp_airflow_lineage/__init__.py
lf_algorithm/plugins/airflow_lineage_agent/mcp_servers/mcp_airflow_lineage/lineage_airflow_server.py
lf_algorithm/plugins/airflow_lineage_agent/mcp_servers/mcp_airflow_lineage/templates.py
lf_algorithm/plugins/java_lineage_agent/__init__.py
lf_algorithm/plugins/java_lineage_agent/java_instructions.py
lf_algorithm/plugins/java_lineage_agent/lineage_agent.py
lf_algorithm/plugins/java_lineage_agent/mcp_servers/__init__.py
lf_algorithm/plugins/java_lineage_agent/mcp_servers/mcp_params.py
lf_algorithm/plugins/java_lineage_agent/mcp_servers/mcp_java_lineage/__init__.py
lf_algorithm/plugins/java_lineage_agent/mcp_servers/mcp_java_lineage/lineage_java_server.py
lf_algorithm/plugins/java_lineage_agent/mcp_servers/mcp_java_lineage/templates.py
lf_algorithm/plugins/python_lineage_agent/__init__.py
lf_algorithm/plugins/python_lineage_agent/lineage_agent.py
lf_algorithm/plugins/python_lineage_agent/python_instructions.py
lf_algorithm/plugins/python_lineage_agent/mcp_servers/__init__.py
lf_algorithm/plugins/python_lineage_agent/mcp_servers/mcp_params.py
lf_algorithm/plugins/python_lineage_agent/mcp_servers/mcp_python_lineage/__init__.py
lf_algorithm/plugins/python_lineage_agent/mcp_servers/mcp_python_lineage/lineage_python_server.py
lf_algorithm/plugins/python_lineage_agent/mcp_servers/mcp_python_lineage/templates.py
lf_algorithm/plugins/spark_lineage_agent/__init__.py
lineagentic_flow-1.0.2.dist-info/licenses/LICENSE
lineagentic_flow-1.0.2.dist-info/METADATA
lineagentic_flow-1.0.2.dist-info/WHEEL
lineagentic_flow-1.0.2.dist-info/entry_points.txt
lineagentic_flow-1.0.2.dist-info/top_level.txt
lineagentic_flow-1.0.2.dist-info/RECORD
