Metadata-Version: 2.4
Name: lineagentic-flow
Version: 1.0.2
Summary: Lineagentic-flow is agentic ai approach for building data lineage across diverse data processing scripts including python, sql, java, airflow, spark, etc.
Author-email: Lineagentic Flow Team <team@lineagentic.com>
License-Expression: MIT
Project-URL: Homepage, https://github.com/lineagentic/lineagentic-flow
Project-URL: Documentation, https://lineagentic-flow.readthedocs.io
Project-URL: Repository, https://github.com/lineagentic/lineagentic-flow
Project-URL: Issues, https://github.com/lineagentic/lineagentic-flow/issues
Keywords: data-lineage,ai-agents,data-processing,lineage-tracking
Classifier: Development Status :: 4 - Beta
Classifier: Intended Audience :: Developers
Classifier: Programming Language :: Python :: 3
Classifier: Programming Language :: Python :: 3.13
Classifier: Topic :: Software Development :: Libraries :: Python Modules
Classifier: Topic :: Scientific/Engineering :: Artificial Intelligence
Requires-Python: >=3.13
License-File: LICENSE
Requires-Dist: anthropic>=0.49.0
Requires-Dist: autogen-agentchat==0.6.1
Requires-Dist: autogen-ext[grpc,mcp,ollama,openai]==0.6.1
Requires-Dist: bs4>=0.0.2
Requires-Dist: fastapi>=0.115.0
Requires-Dist: gradio>=5.22.0
Requires-Dist: httpx>=0.28.1
Requires-Dist: ipykernel>=6.29.5
Requires-Dist: ipython<9.0.0,>=8.0.0
Requires-Dist: ipywidgets>=8.1.5
Requires-Dist: jupyter>=1.1.1
Requires-Dist: langchain-anthropic>=0.3.10
Requires-Dist: langchain-community>=0.3.20
Requires-Dist: langchain-experimental>=0.3.4
Requires-Dist: langchain-openai>=0.3.9
Requires-Dist: langgraph>=0.3.18
Requires-Dist: langgraph-checkpoint-sqlite>=2.0.6
Requires-Dist: langsmith>=0.3.18
Requires-Dist: lxml>=5.3.1
Requires-Dist: mcp-server-fetch>=2025.1.17
Requires-Dist: mcp[cli]>=1.5.0
Requires-Dist: mysql-connector-python>=8.0.0
Requires-Dist: nbformat>=4.2.0
Requires-Dist: neo4j>=5.20.0
Requires-Dist: openai==1.91.0
Requires-Dist: openai-agents==0.0.19
Requires-Dist: playwright>=1.51.0
Requires-Dist: plotly>=6.0.1
Requires-Dist: polygon-api-client>=1.14.5
Requires-Dist: psutil>=7.0.0
Requires-Dist: pypdf>=5.4.0
Requires-Dist: pypdf2>=3.0.1
Requires-Dist: python-dotenv>=1.0.1
Requires-Dist: requests>=2.32.3
Requires-Dist: semantic-kernel>=1.25.0
Requires-Dist: sendgrid>=6.11.0
Requires-Dist: setuptools>=78.1.0
Requires-Dist: smithery>=0.1.0
Requires-Dist: speedtest-cli>=2.1.3
Requires-Dist: watchdog>=6.0.0
Requires-Dist: wikipedia>=1.4.0
Provides-Extra: dev
Requires-Dist: ipykernel>=6.29.5; extra == "dev"
Requires-Dist: pytest>=8.0.0; extra == "dev"
Requires-Dist: pytest-asyncio>=0.24.0; extra == "dev"
Dynamic: license-file
